caravan_tools/__init__.py
caravan_tools/__main__.py
caravan_tools/cards.py
caravan_tools/moves.py
caravanassets/__init__.py
caravanassets/__main__.py
caravanassets/cards.py
caravanassets/moves.py
caravanassets-0.1.3.dist-info/LICENSE.txt
caravanassets-0.1.3.dist-info/METADATA
caravanassets-0.1.3.dist-info/WHEEL
caravanassets-0.1.3.dist-info/top_level.txt
caravanassets-0.1.3.dist-info/RECORD
