Metadata-Version: 2.1
Name: caravanassets
Version: 0.1.3
Summary: This is a python package for implementing the card game Caravan
Home-page: https://github.com/Anritab/CaravanCardGame
Download-URL: https://github.com/Anritab/CaravanCardGame/issues
Author: Anri Tabuev
Author-email: Anri Tabuev <anri.tabuev@gmail.com>
License: MIT
Project-URL: Homepage, https://github.com/Anritab/CaravanCardGame
Project-URL: Bug Tracker, https://github.com/Anritab/CaravanCardGame/issues
Keywords: caravan,card,cardgame,game,fallout
Classifier: Programming Language :: Python :: 3
Classifier: License :: OSI Approved :: MIT License
Classifier: Operating System :: Unix
Requires-Python: >=3.9
License-File: LICENSE.txt
Requires-Dist: click
